rpn/__init__.py
rpn/preparePrimeData.py
rpn/rpnDebug.py
rpn/rpnGenerator.py
rpn/rpnGlobals.py
rpn/rpnKeyboard.py
rpn/rpnPersistence.py
rpn/rpnSettings.py
rpn/rpnUtils.py
rpn/rpnVersion.py
rpn/rpndata/balanced_primes.cache
rpn/rpndata/cousin_primes.cache
rpn/rpndata/double_balanced_primes.cache
rpn/rpndata/huge_primes.cache
rpn/rpndata/isolated_primes.cache
rpn/rpndata/large_primes.cache
rpn/rpndata/octy_primes.cache
rpn/rpndata/quad_primes.cache
rpn/rpndata/quadruple_balanced_primes.cache
rpn/rpndata/quint_primes.cache
rpn/rpndata/sext_primes.cache
rpn/rpndata/sexy_primes.cache
rpn/rpndata/sexy_quadruplets.cache
rpn/rpndata/sexy_triplets.cache
rpn/rpndata/small_primes.cache
rpn/rpndata/sophie_primes.cache
rpn/rpndata/triple_balanced_primes.cache
rpn/rpndata/triplet_primes.cache
rpn/rpndata/twin_primes.cache
rpnChiladaData-1.1.0.dist-info/LICENSE
rpnChiladaData-1.1.0.dist-info/METADATA
rpnChiladaData-1.1.0.dist-info/WHEEL
rpnChiladaData-1.1.0.dist-info/top_level.txt
rpnChiladaData-1.1.0.dist-info/RECORD
